super_map/__init__.py
super_map/neo_map.py
super_map-1.3.3.dist-info/METADATA
super_map-1.3.3.dist-info/WHEEL
super_map-1.3.3.dist-info/top_level.txt
super_map-1.3.3.dist-info/RECORD
