Metadata-Version: 2.1
Name: super-map
Version: 1.3.3
Summary: Like dict, but easier
Home-page: https://github.com/jeff-hykin/super_map.git
Author: Jeff Hykin
Author-email: jeff.hykin@gmail.com
License: MIT
Platform: UNKNOWN
Requires-Python: >=3.6
Requires-Dist: json-fix (>=0.1.3)
